simpleavs
