Metadata-Version: 1.1
Name: simpleavs
Version: 0.3.2
Summary: Simple AVS API Client (Amazon Alexa Voice Service) for v20160207
Home-page: https://github.com/robladbrook/simple-avs
Author: Rob Ladbrook
Author-email: simpleavs@slyfx.com
License: UNKNOWN
Download-URL: https://github.com/robladbrook/simple-avs/tarball/0.3.2
Keywords: avs,alexa,amazon,voice
Platform: UNKNOWN
